[{ "_id" : { "$oid" : "5a00d60a1504d918793268e9" }, "vendorId" : 1739, "productId" : 29703, "path" : "\\\\?\\hid#syn1b81&col03#5&d0db040&0&0002#{4d1e55b2-f16f-11cf-88cb-001111000030}, \\\\?\\hid#syn1b81&col04#5&d0db040&0&0003#{4d1e55b2-f16f-11cf-88cb-001111000030}, \\\\?\\hid#syn1b81&col01#5&d0db040&0&0000#{4d1e55b2-f16f-11cf-88cb-001111000030}, \\\\?\\hid#syn1b81&col02#5&d0db040&0&0001#{4d1e55b2-f16f-11cf-88cb-001111000030}", "serialNumber" : "9999", "manufacturer" : "Microsoft", "product" : "HIDI2C Device", "release" : 6, "interface" : -1, "usagePage" : "13, 65280, 1, 13", "usage" : "14, 1, 2, 5", "userId" : "Jason", "__v" : 0 },{ "_id" : { "$oid" : "5a00d60a1504d918793268ea" }, "vendorId" : 1151, "productId" : 295, "path" : "\\\\?\\hid#vid_047f&pid_0127&col01#6&34dda44b&0&0000#{4d1e55b2-f16f-11cf-88cb-001111000030}, \\\\?\\hid#vid_047f&pid_0127&col02#6&34dda44b&0&0001#{4d1e55b2-f16f-11cf-88cb-001111000030}, \\\\?\\hid#vid_047f&pid_0127&col03#6&34dda44b&0&0002#{4d1e55b2-f16f-11cf-88cb-001111000030}", "serialNumber" : "bebd4221027e6e438947a76467a93cd1", "manufacturer" : "Plantronics", "product" : "Plantronics Voyager Focus UC", "release" : 260, "interface" : -1, "usagePage" : "65440, 65442, 12", "usage" : "1, 1, 1", "userId" : "Jason", "__v" : 0 },{ "_id" : { "$oid" : "5a00d60a1504d918793268eb" }, "vendorId" : 1266, "productId" : 2422, "path" : "\\\\?\\hid#vid_04f2&pid_0976&mi_00#7&601cf38&0&0000#{4d1e55b2-f16f-11cf-88cb-001111000030}, \\\\?\\hid#vid_04f2&pid_0976&mi_02#7&20cd9a37&0&0000#{4d1e55b2-f16f-11cf-88cb-001111000030}, \\\\?\\hid#vid_04f2&pid_0976&mi_01&col01#7&33fdb675&0&0000#{4d1e55b2-f16f-11cf-88cb-001111000030}, \\\\?\\hid#vid_04f2&pid_0976&mi_01&col02#7&33fdb675&0&0001#{4d1e55b2-f16f-11cf-88cb-001111000030}, \\\\?\\hid#vid_04f2&pid_0976&mi_01&col03#7&33fdb675&0&0002#{4d1e55b2-f16f-11cf-88cb-001111000030}", "manufacturer" : "Chicony", "product" : "Wireless Device", "release" : 288, "interface" : 0, "usagePage" : "1, 1, 12, 1, 65281", "usage" : "6, 2, 1, 128, 4", "userId" : "Jason", "__v" : 0 },{ "_id" : { "$oid" : "5a00d60a1504d918793268ec" }, "vendorId" : 11254, "productId" : 41110, "path" : "\\\\?\\hid#hidclass&col01#1&2d595ca7&0&0000#{4d1e55b2-f16f-11cf-88cb-001111000030}, \\\\?\\hid#hidclass&col02#1&2d595ca7&0&0001#{4d1e55b2-f16f-11cf-88cb-001111000030}", "manufacturer" : "Acer Inc.", "product" : "Launch Manager Wireless Device", "release" : 1, "interface" : -1, "usagePage" : "65280, 1", "usage" : "1, 12", "userId" : "Jason", "__v" : 0 },{ "_id" : { "$oid" : "5a00d6581504d918793268ef" }, "vendorId" : 1133, "productId" : 50475, "path" : "\\\\?\\hid#vid_046d&pid_c52b&mi_00#7&fd36ce2&0&0000#{4d1e55b2-f16f-11cf-88cb-001111000030}, \\\\?\\hid#vid_046d&pid_c52b&mi_02&col01#7&3148838c&0&0000#{4d1e55b2-f16f-11cf-88cb-001111000030}, \\\\?\\hid#vid_046d&pid_c52b&mi_02&col02#7&3148838c&0&0001#{4d1e55b2-f16f-11cf-88cb-001111000030}, \\\\?\\hid#vid_046d&pid_c52b&mi_02&col03#7&3148838c&0&0002#{4d1e55b2-f16f-11cf-88cb-001111000030}, \\\\?\\hid#vid_046d&pid_c52b&mi_01&col01#7&33aaaaa4&0&0000#{4d1e55b2-f16f-11cf-88cb-001111000030}, \\\\?\\hid#vid_046d&pid_c52b&mi_01&col02#7&33aaaaa4&0&0001#{4d1e55b2-f16f-11cf-88cb-001111000030}, \\\\?\\hid#vid_046d&pid_c52b&mi_01&col03#7&33aaaaa4&0&0002#{4d1e55b2-f16f-11cf-88cb-001111000030}, \\\\?\\hid#vid_046d&pid_c52b&mi_01&col04#7&33aaaaa4&0&0003#{4d1e55b2-f16f-11cf-88cb-001111000030}", "manufacturer" : "Logitech", "product" : "USB Receiver", "release" : 4611, "interface" : 0, "usagePage" : "1, 65280, 65280, 65280, 1, 12, 1, 65468", "usage" : "6, 1, 2, 4, 2, 1, 128, 136", "userId" : "hello@email.com", "__v" : 0 },{ "_id" : { "$oid" : "5a00d6581504d918793268f0" }, "vendorId" : 48879, "productId" : 65261, "path" : "\\\\?\\hid#lenovovhid#1&632d18&0&0000#{4d1e55b2-f16f-11cf-88cb-001111000030}", "serialNumber" : "UMDF Virtual hidmini device Serial Number string", "manufacturer" : "UMDF Virtual hidmini device Manufacturer string", "product" : "UMDF Virtual hidmini device Product string", "release" : 257, "interface" : -1, "usagePage" : "1", "usage" : "12", "userId" : "hello@email.com", "__v" : 0 },{ "_id" : { "$oid" : "5a00d8221504d918793268f1" }, "vendorId" : 1133, "productId" : 50479, "path" : "\\\\?\\hid#vid_046d&pid_c52f&mi_00#7&23151d8d&0&0000#{4d1e55b2-f16f-11cf-88cb-001111000030}, \\\\?\\hid#vid_046d&pid_c52f&mi_01&col02#7&643469c&0&0001#{4d1e55b2-f16f-11cf-88cb-001111000030}, \\\\?\\hid#vid_046d&pid_c52f&mi_01&col03#7&643469c&0&0002#{4d1e55b2-f16f-11cf-88cb-001111000030}, \\\\?\\hid#vid_046d&pid_c52f&mi_01&col01#7&643469c&0&0000#{4d1e55b2-f16f-11cf-88cb-001111000030}", "manufacturer" : "Logitech", "product" : "USB Receiver", "release" : 8705, "interface" : 0, "usagePage" : "1, 65280, 65280, 12", "usage" : "2, 1, 2, 1", "userId" : "Justin", "__v" : 0 },{ "_id" : { "$oid" : "5a00d8221504d918793268f2" }, "vendorId" : 1, "productId" : 1, "path" : "\\\\?\\hid#hpq6001#3&9489f59&0&0000#{4d1e55b2-f16f-11cf-88cb-001111000030}", "release" : 1, "interface" : -1, "usagePage" : "1", "usage" : "12", "userId" : "Justin", "__v" : 0 },{ "_id" : { "$oid" : "5a00d8351504d918793268f3" }, "vendorId" : 1133, "productId" : 50475, "path" : "\\\\?\\hid#vid_046d&pid_c52b&mi_00#7&fd36ce2&0&0000#{4d1e55b2-f16f-11cf-88cb-001111000030}, \\\\?\\hid#vid_046d&pid_c52b&mi_02&col01#7&3148838c&0&0000#{4d1e55b2-f16f-11cf-88cb-001111000030}, \\\\?\\hid#vid_046d&pid_c52b&mi_02&col02#7&3148838c&0&0001#{4d1e55b2-f16f-11cf-88cb-001111000030}, \\\\?\\hid#vid_046d&pid_c52b&mi_02&col03#7&3148838c&0&0002#{4d1e55b2-f16f-11cf-88cb-001111000030}, \\\\?\\hid#vid_046d&pid_c52b&mi_01&col01#7&33aaaaa4&0&0000#{4d1e55b2-f16f-11cf-88cb-001111000030}, \\\\?\\hid#vid_046d&pid_c52b&mi_01&col02#7&33aaaaa4&0&0001#{4d1e55b2-f16f-11cf-88cb-001111000030}, \\\\?\\hid#vid_046d&pid_c52b&mi_01&col03#7&33aaaaa4&0&0002#{4d1e55b2-f16f-11cf-88cb-001111000030}, \\\\?\\hid#vid_046d&pid_c52b&mi_01&col04#7&33aaaaa4&0&0003#{4d1e55b2-f16f-11cf-88cb-001111000030}", "manufacturer" : "Logitech", "product" : "USB Receiver", "release" : 4611, "interface" : 0, "usagePage" : "1, 65280, 65280, 65280, 1, 12, 1, 65468", "usage" : "6, 1, 2, 4, 2, 1, 128, 136", "userId" : "afasd", "__v" : 0 },{ "_id" : { "$oid" : "5a00d8351504d918793268f4" }, "vendorId" : 48879, "productId" : 65261, "path" : "\\\\?\\hid#lenovovhid#1&632d18&0&0000#{4d1e55b2-f16f-11cf-88cb-001111000030}", "serialNumber" : "UMDF Virtual hidmini device Serial Number string", "manufacturer" : "UMDF Virtual hidmini device Manufacturer string", "product" : "UMDF Virtual hidmini device Product string", "release" : 257, "interface" : -1, "usagePage" : "1", "usage" : "12", "userId" : "afasd", "__v" : 0 },{ "_id" : { "$oid" : "5a00e0db1504d918793268fc" }, "vendorId" : 1133, "productId" : 50475, "path" : "\\\\?\\hid#vid_046d&pid_c52b&mi_00#7&fd36ce2&0&0000#{4d1e55b2-f16f-11cf-88cb-001111000030}, \\\\?\\hid#vid_046d&pid_c52b&mi_02&col01#7&3148838c&0&0000#{4d1e55b2-f16f-11cf-88cb-001111000030}, \\\\?\\hid#vid_046d&pid_c52b&mi_02&col02#7&3148838c&0&0001#{4d1e55b2-f16f-11cf-88cb-001111000030}, \\\\?\\hid#vid_046d&pid_c52b&mi_02&col03#7&3148838c&0&0002#{4d1e55b2-f16f-11cf-88cb-001111000030}, \\\\?\\hid#vid_046d&pid_c52b&mi_01&col01#7&33aaaaa4&0&0000#{4d1e55b2-f16f-11cf-88cb-001111000030}, \\\\?\\hid#vid_046d&pid_c52b&mi_01&col02#7&33aaaaa4&0&0001#{4d1e55b2-f16f-11cf-88cb-001111000030}, \\\\?\\hid#vid_046d&pid_c52b&mi_01&col03#7&33aaaaa4&0&0002#{4d1e55b2-f16f-11cf-88cb-001111000030}, \\\\?\\hid#vid_046d&pid_c52b&mi_01&col04#7&33aaaaa4&0&0003#{4d1e55b2-f16f-11cf-88cb-001111000030}", "manufacturer" : "Logitech", "product" : "USB Receiver", "release" : 4611, "interface" : 0, "usagePage" : "1, 65280, 65280, 65280, 1, 12, 1, 65468", "usage" : "6, 1, 2, 4, 2, 1, 128, 136", "userId" : "adsfad@us.com", "__v" : 0 },{ "_id" : { "$oid" : "5a00e0db1504d918793268fd" }, "vendorId" : 48879, "productId" : 65261, "path" : "\\\\?\\hid#lenovovhid#1&632d18&0&0000#{4d1e55b2-f16f-11cf-88cb-001111000030}", "serialNumber" : "UMDF Virtual hidmini device Serial Number string", "manufacturer" : "UMDF Virtual hidmini device Manufacturer string", "product" : "UMDF Virtual hidmini device Product string", "release" : 257, "interface" : -1, "usagePage" : "1", "usage" : "12", "userId" : "adsfad@us.com", "__v" : 0 },{ "_id" : { "$oid" : "5a00e0e91504d918793268fe" }, "vendorId" : 1133, "productId" : 50475, "path" : "\\\\?\\hid#vid_046d&pid_c52b&mi_00#7&fd36ce2&0&0000#{4d1e55b2-f16f-11cf-88cb-001111000030}, \\\\?\\hid#vid_046d&pid_c52b&mi_02&col01#7&3148838c&0&0000#{4d1e55b2-f16f-11cf-88cb-001111000030}, \\\\?\\hid#vid_046d&pid_c52b&mi_02&col02#7&3148838c&0&0001#{4d1e55b2-f16f-11cf-88cb-001111000030}, \\\\?\\hid#vid_046d&pid_c52b&mi_02&col03#7&3148838c&0&0002#{4d1e55b2-f16f-11cf-88cb-001111000030}, \\\\?\\hid#vid_046d&pid_c52b&mi_01&col01#7&33aaaaa4&0&0000#{4d1e55b2-f16f-11cf-88cb-001111000030}, \\\\?\\hid#vid_046d&pid_c52b&mi_01&col02#7&33aaaaa4&0&0001#{4d1e55b2-f16f-11cf-88cb-001111000030}, \\\\?\\hid#vid_046d&pid_c52b&mi_01&col03#7&33aaaaa4&0&0002#{4d1e55b2-f16f-11cf-88cb-001111000030}, \\\\?\\hid#vid_046d&pid_c52b&mi_01&col04#7&33aaaaa4&0&0003#{4d1e55b2-f16f-11cf-88cb-001111000030}", "manufacturer" : "Logitech", "product" : "USB Receiver", "release" : 4611, "interface" : 0, "usagePage" : "1, 65280, 65280, 65280, 1, 12, 1, 65468", "usage" : "6, 1, 2, 4, 2, 1, 128, 136", "userId" : "asdf", "__v" : 0 },{ "_id" : { "$oid" : "5a00e0e91504d918793268ff" }, "vendorId" : 48879, "productId" : 65261, "path" : "\\\\?\\hid#lenovovhid#1&632d18&0&0000#{4d1e55b2-f16f-11cf-88cb-001111000030}", "serialNumber" : "UMDF Virtual hidmini device Serial Number string", "manufacturer" : "UMDF Virtual hidmini device Manufacturer string", "product" : "UMDF Virtual hidmini device Product string", "release" : 257, "interface" : -1, "usagePage" : "1", "usage" : "12", "userId" : "asdf", "__v" : 0 },{ "_id" : { "$oid" : "5a00e1c01504d91879326901" }, "vendorId" : 1739, "productId" : 29703, "path" : "\\\\?\\hid#syn1b81&col03#5&d0db040&0&0002#{4d1e55b2-f16f-11cf-88cb-001111000030}, \\\\?\\hid#syn1b81&col04#5&d0db040&0&0003#{4d1e55b2-f16f-11cf-88cb-001111000030}, \\\\?\\hid#syn1b81&col01#5&d0db040&0&0000#{4d1e55b2-f16f-11cf-88cb-001111000030}, \\\\?\\hid#syn1b81&col02#5&d0db040&0&0001#{4d1e55b2-f16f-11cf-88cb-001111000030}", "serialNumber" : "9999", "manufacturer" : "Microsoft", "product" : "HIDI2C Device", "release" : 6, "interface" : -1, "usagePage" : "13, 65280, 1, 13", "usage" : "14, 1, 2, 5", "userId" : "Jason@aosidasiond.asdas", "__v" : 0 },{ "_id" : { "$oid" : "5a00e1c01504d91879326902" }, "vendorId" : 11254, "productId" : 41110, "path" : "\\\\?\\hid#hidclass&col01#1&2d595ca7&0&0000#{4d1e55b2-f16f-11cf-88cb-001111000030}, \\\\?\\hid#hidclass&col02#1&2d595ca7&0&0001#{4d1e55b2-f16f-11cf-88cb-001111000030}", "manufacturer" : "Acer Inc.", "product" : "Launch Manager Wireless Device", "release" : 1, "interface" : -1, "usagePage" : "65280, 1", "usage" : "1, 12", "userId" : "Jason@aosidasiond.asdas", "__v" : 0 },{ "_id" : { "$oid" : "5a00e1c01504d91879326903" }, "vendorId" : 1151, "productId" : 295, "path" : "\\\\?\\hid#vid_047f&pid_0127&col01#6&34dda44b&0&0000#{4d1e55b2-f16f-11cf-88cb-001111000030}, \\\\?\\hid#vid_047f&pid_0127&col02#6&34dda44b&0&0001#{4d1e55b2-f16f-11cf-88cb-001111000030}, \\\\?\\hid#vid_047f&pid_0127&col03#6&34dda44b&0&0002#{4d1e55b2-f16f-11cf-88cb-001111000030}", "serialNumber" : "bebd4221027e6e438947a76467a93cd1", "manufacturer" : "Plantronics", "product" : "Plantronics Voyager Focus UC", "release" : 260, "interface" : -1, "usagePage" : "65440, 65442, 12", "usage" : "1, 1, 1", "userId" : "Jason@aosidasiond.asdas", "__v" : 0 },{ "_id" : { "$oid" : "5a00e1c01504d91879326904" }, "vendorId" : 1266, "productId" : 2422, "path" : "\\\\?\\hid#vid_04f2&pid_0976&mi_00#7&601cf38&0&0000#{4d1e55b2-f16f-11cf-88cb-001111000030}, \\\\?\\hid#vid_04f2&pid_0976&mi_02#7&20cd9a37&0&0000#{4d1e55b2-f16f-11cf-88cb-001111000030}, \\\\?\\hid#vid_04f2&pid_0976&mi_01&col01#7&33fdb675&0&0000#{4d1e55b2-f16f-11cf-88cb-001111000030}, \\\\?\\hid#vid_04f2&pid_0976&mi_01&col02#7&33fdb675&0&0001#{4d1e55b2-f16f-11cf-88cb-001111000030}, \\\\?\\hid#vid_04f2&pid_0976&mi_01&col03#7&33fdb675&0&0002#{4d1e55b2-f16f-11cf-88cb-001111000030}", "manufacturer" : "Chicony", "product" : "Wireless Device", "release" : 288, "interface" : 0, "usagePage" : "1, 1, 12, 1, 65281", "usage" : "6, 2, 1, 128, 4", "userId" : "Jason@aosidasiond.asdas", "__v" : 0 },{ "_id" : { "$oid" : "5a00e1cd1504d91879326906" }, "vendorId" : 1739, "productId" : 29703, "path" : "\\\\?\\hid#syn1b81&col03#5&d0db040&0&0002#{4d1e55b2-f16f-11cf-88cb-001111000030}, \\\\?\\hid#syn1b81&col04#5&d0db040&0&0003#{4d1e55b2-f16f-11cf-88cb-001111000030}, \\\\?\\hid#syn1b81&col01#5&d0db040&0&0000#{4d1e55b2-f16f-11cf-88cb-001111000030}, \\\\?\\hid#syn1b81&col02#5&d0db040&0&0001#{4d1e55b2-f16f-11cf-88cb-001111000030}", "serialNumber" : "9999", "manufacturer" : "Microsoft", "product" : "HIDI2C Device", "release" : 6, "interface" : -1, "usagePage" : "13, 65280, 1, 13", "usage" : "14, 1, 2, 5", "userId" : "Jason@Thai.com", "__v" : 0 },{ "_id" : { "$oid" : "5a00e1cd1504d91879326907" }, "vendorId" : 11254, "productId" : 41110, "path" : "\\\\?\\hid#hidclass&col01#1&2d595ca7&0&0000#{4d1e55b2-f16f-11cf-88cb-001111000030}, \\\\?\\hid#hidclass&col02#1&2d595ca7&0&0001#{4d1e55b2-f16f-11cf-88cb-001111000030}", "manufacturer" : "Acer Inc.", "product" : "Launch Manager Wireless Device", "release" : 1, "interface" : -1, "usagePage" : "65280, 1", "usage" : "1, 12", "userId" : "Jason@Thai.com", "__v" : 0 },{ "_id" : { "$oid" : "5a00e1cd1504d91879326908" }, "vendorId" : 1151, "productId" : 295, "path" : "\\\\?\\hid#vid_047f&pid_0127&col01#6&34dda44b&0&0000#{4d1e55b2-f16f-11cf-88cb-001111000030}, \\\\?\\hid#vid_047f&pid_0127&col02#6&34dda44b&0&0001#{4d1e55b2-f16f-11cf-88cb-001111000030}, \\\\?\\hid#vid_047f&pid_0127&col03#6&34dda44b&0&0002#{4d1e55b2-f16f-11cf-88cb-001111000030}", "serialNumber" : "bebd4221027e6e438947a76467a93cd1", "manufacturer" : "Plantronics", "product" : "Plantronics Voyager Focus UC", "release" : 260, "interface" : -1, "usagePage" : "65440, 65442, 12", "usage" : "1, 1, 1", "userId" : "Jason@Thai.com", "__v" : 0 },{ "_id" : { "$oid" : "5a00e1cd1504d91879326909" }, "vendorId" : 1266, "productId" : 2422, "path" : "\\\\?\\hid#vid_04f2&pid_0976&mi_00#7&601cf38&0&0000#{4d1e55b2-f16f-11cf-88cb-001111000030}, \\\\?\\hid#vid_04f2&pid_0976&mi_02#7&20cd9a37&0&0000#{4d1e55b2-f16f-11cf-88cb-001111000030}, \\\\?\\hid#vid_04f2&pid_0976&mi_01&col01#7&33fdb675&0&0000#{4d1e55b2-f16f-11cf-88cb-001111000030}, \\\\?\\hid#vid_04f2&pid_0976&mi_01&col02#7&33fdb675&0&0001#{4d1e55b2-f16f-11cf-88cb-001111000030}, \\\\?\\hid#vid_04f2&pid_0976&mi_01&col03#7&33fdb675&0&0002#{4d1e55b2-f16f-11cf-88cb-001111000030}", "manufacturer" : "Chicony", "product" : "Wireless Device", "release" : 288, "interface" : 0, "usagePage" : "1, 1, 12, 1, 65281", "usage" : "6, 2, 1, 128, 4", "userId" : "Jason@Thai.com", "__v" : 0 },{ "_id" : { "$oid" : "5a00e2f11504d9187932690c" }, "vendorId" : 1133, "productId" : 50475, "path" : "\\\\?\\hid#vid_046d&pid_c52b&mi_00#7&fd36ce2&0&0000#{4d1e55b2-f16f-11cf-88cb-001111000030}, \\\\?\\hid#vid_046d&pid_c52b&mi_02&col01#7&3148838c&0&0000#{4d1e55b2-f16f-11cf-88cb-001111000030}, \\\\?\\hid#vid_046d&pid_c52b&mi_02&col02#7&3148838c&0&0001#{4d1e55b2-f16f-11cf-88cb-001111000030}, \\\\?\\hid#vid_046d&pid_c52b&mi_02&col03#7&3148838c&0&0002#{4d1e55b2-f16f-11cf-88cb-001111000030}, \\\\?\\hid#vid_046d&pid_c52b&mi_01&col01#7&33aaaaa4&0&0000#{4d1e55b2-f16f-11cf-88cb-001111000030}, \\\\?\\hid#vid_046d&pid_c52b&mi_01&col02#7&33aaaaa4&0&0001#{4d1e55b2-f16f-11cf-88cb-001111000030}, \\\\?\\hid#vid_046d&pid_c52b&mi_01&col03#7&33aaaaa4&0&0002#{4d1e55b2-f16f-11cf-88cb-001111000030}, \\\\?\\hid#vid_046d&pid_c52b&mi_01&col04#7&33aaaaa4&0&0003#{4d1e55b2-f16f-11cf-88cb-001111000030}", "manufacturer" : "Logitech", "product" : "USB Receiver", "release" : 4611, "interface" : 0, "usagePage" : "1, 65280, 65280, 65280, 1, 12, 1, 65468", "usage" : "6, 1, 2, 4, 2, 1, 128, 136", "userId" : "asdf@utexes.com", "__v" : 0 },{ "_id" : { "$oid" : "5a00e2f11504d9187932690d" }, "vendorId" : 48879, "productId" : 65261, "path" : "\\\\?\\hid#lenovovhid#1&632d18&0&0000#{4d1e55b2-f16f-11cf-88cb-001111000030}", "serialNumber" : "UMDF Virtual hidmini device Serial Number string", "manufacturer" : "UMDF Virtual hidmini device Manufacturer string", "product" : "UMDF Virtual hidmini device Product string", "release" : 257, "interface" : -1, "usagePage" : "1", "usage" : "12", "userId" : "asdf@utexes.com", "__v" : 0 },{ "_id" : { "$oid" : "5a00e30d1504d9187932690f" }, "vendorId" : 48879, "productId" : 65261, "path" : "\\\\?\\hid#lenovovhid#1&632d18&0&0000#{4d1e55b2-f16f-11cf-88cb-001111000030}", "serialNumber" : "UMDF Virtual hidmini device Serial Number string", "manufacturer" : "UMDF Virtual hidmini device Manufacturer string", "product" : "UMDF Virtual hidmini device Product string", "release" : 257, "interface" : -1, "usagePage" : "1", "usage" : "12", "userId" : "asdf@g.com", "__v" : 0 },{ "_id" : { "$oid" : "5a00e30d1504d91879326910" }, "vendorId" : 1133, "productId" : 50475, "path" : "\\\\?\\hid#vid_046d&pid_c52b&mi_00#7&fd36ce2&0&0000#{4d1e55b2-f16f-11cf-88cb-001111000030}, \\\\?\\hid#vid_046d&pid_c52b&mi_02&col01#7&3148838c&0&0000#{4d1e55b2-f16f-11cf-88cb-001111000030}, \\\\?\\hid#vid_046d&pid_c52b&mi_02&col02#7&3148838c&0&0001#{4d1e55b2-f16f-11cf-88cb-001111000030}, \\\\?\\hid#vid_046d&pid_c52b&mi_02&col03#7&3148838c&0&0002#{4d1e55b2-f16f-11cf-88cb-001111000030}, \\\\?\\hid#vid_046d&pid_c52b&mi_01&col01#7&33aaaaa4&0&0000#{4d1e55b2-f16f-11cf-88cb-001111000030}, \\\\?\\hid#vid_046d&pid_c52b&mi_01&col02#7&33aaaaa4&0&0001#{4d1e55b2-f16f-11cf-88cb-001111000030}, \\\\?\\hid#vid_046d&pid_c52b&mi_01&col03#7&33aaaaa4&0&0002#{4d1e55b2-f16f-11cf-88cb-001111000030}, \\\\?\\hid#vid_046d&pid_c52b&mi_01&col04#7&33aaaaa4&0&0003#{4d1e55b2-f16f-11cf-88cb-001111000030}", "manufacturer" : "Logitech", "product" : "USB Receiver", "release" : 4611, "interface" : 0, "usagePage" : "1, 65280, 65280, 65280, 1, 12, 1, 65468", "usage" : "6, 1, 2, 4, 2, 1, 128, 136", "userId" : "asdf@g.com", "__v" : 0 },{ "_id" : { "$oid" : "5a00e3591504d91879326911" }, "vendorId" : 1739, "productId" : 29703, "path" : "\\\\?\\hid#syn1b81&col03#5&d0db040&0&0002#{4d1e55b2-f16f-11cf-88cb-001111000030}, \\\\?\\hid#syn1b81&col04#5&d0db040&0&0003#{4d1e55b2-f16f-11cf-88cb-001111000030}, \\\\?\\hid#syn1b81&col01#5&d0db040&0&0000#{4d1e55b2-f16f-11cf-88cb-001111000030}, \\\\?\\hid#syn1b81&col02#5&d0db040&0&0001#{4d1e55b2-f16f-11cf-88cb-001111000030}", "serialNumber" : "9999", "manufacturer" : "Microsoft", "product" : "HIDI2C Device", "release" : 6, "interface" : -1, "usagePage" : "13, 65280, 1, 13", "usage" : "14, 1, 2, 5", "userId" : "Jason@sadsa.sdas", "__v" : 0 },{ "_id" : { "$oid" : "5a00e3591504d91879326912" }, "vendorId" : 11254, "productId" : 41110, "path" : "\\\\?\\hid#hidclass&col01#1&2d595ca7&0&0000#{4d1e55b2-f16f-11cf-88cb-001111000030}, \\\\?\\hid#hidclass&col02#1&2d595ca7&0&0001#{4d1e55b2-f16f-11cf-88cb-001111000030}", "manufacturer" : "Acer Inc.", "product" : "Launch Manager Wireless Device", "release" : 1, "interface" : -1, "usagePage" : "65280, 1", "usage" : "1, 12", "userId" : "Jason@sadsa.sdas", "__v" : 0 },{ "_id" : { "$oid" : "5a00e3591504d91879326913" }, "vendorId" : 1266, "productId" : 2422, "path" : "\\\\?\\hid#vid_04f2&pid_0976&mi_00#7&601cf38&0&0000#{4d1e55b2-f16f-11cf-88cb-001111000030}, \\\\?\\hid#vid_04f2&pid_0976&mi_02#7&20cd9a37&0&0000#{4d1e55b2-f16f-11cf-88cb-001111000030}, \\\\?\\hid#vid_04f2&pid_0976&mi_01&col01#7&33fdb675&0&0000#{4d1e55b2-f16f-11cf-88cb-001111000030}, \\\\?\\hid#vid_04f2&pid_0976&mi_01&col02#7&33fdb675&0&0001#{4d1e55b2-f16f-11cf-88cb-001111000030}, \\\\?\\hid#vid_04f2&pid_0976&mi_01&col03#7&33fdb675&0&0002#{4d1e55b2-f16f-11cf-88cb-001111000030}", "manufacturer" : "Chicony", "product" : "Wireless Device", "release" : 288, "interface" : 0, "usagePage" : "1, 1, 12, 1, 65281", "usage" : "6, 2, 1, 128, 4", "userId" : "Jason@sadsa.sdas", "__v" : 0 },{ "_id" : { "$oid" : "5a00e3591504d91879326914" }, "vendorId" : 1151, "productId" : 295, "path" : "\\\\?\\hid#vid_047f&pid_0127&col01#6&34dda44b&0&0000#{4d1e55b2-f16f-11cf-88cb-001111000030}, \\\\?\\hid#vid_047f&pid_0127&col02#6&34dda44b&0&0001#{4d1e55b2-f16f-11cf-88cb-001111000030}, \\\\?\\hid#vid_047f&pid_0127&col03#6&34dda44b&0&0002#{4d1e55b2-f16f-11cf-88cb-001111000030}", "serialNumber" : "bebd4221027e6e438947a76467a93cd1", "manufacturer" : "Plantronics", "product" : "Plantronics Voyager Focus UC", "release" : 260, "interface" : -1, "usagePage" : "65440, 65442, 12", "usage" : "1, 1, 1", "userId" : "Jason@sadsa.sdas", "__v" : 0 },{ "_id" : { "$oid" : "5a00e3da1504d91879326917" }, "vendorId" : 48879, "productId" : 65261, "path" : "\\\\?\\hid#lenovovhid#1&632d18&0&0000#{4d1e55b2-f16f-11cf-88cb-001111000030}", "serialNumber" : "UMDF Virtual hidmini device Serial Number string", "manufacturer" : "UMDF Virtual hidmini device Manufacturer string", "product" : "UMDF Virtual hidmini device Product string", "release" : 257, "interface" : -1, "usagePage" : "1", "usage" : "12", "userId" : "asdf@b.com", "__v" : 0 },{ "_id" : { "$oid" : "5a00e3da1504d91879326918" }, "vendorId" : 1133, "productId" : 50475, "path" : "\\\\?\\hid#vid_046d&pid_c52b&mi_00#7&fd36ce2&0&0000#{4d1e55b2-f16f-11cf-88cb-001111000030}, \\\\?\\hid#vid_046d&pid_c52b&mi_02&col01#7&3148838c&0&0000#{4d1e55b2-f16f-11cf-88cb-001111000030}, \\\\?\\hid#vid_046d&pid_c52b&mi_02&col02#7&3148838c&0&0001#{4d1e55b2-f16f-11cf-88cb-001111000030}, \\\\?\\hid#vid_046d&pid_c52b&mi_02&col03#7&3148838c&0&0002#{4d1e55b2-f16f-11cf-88cb-001111000030}, \\\\?\\hid#vid_046d&pid_c52b&mi_01&col01#7&33aaaaa4&0&0000#{4d1e55b2-f16f-11cf-88cb-001111000030}, \\\\?\\hid#vid_046d&pid_c52b&mi_01&col02#7&33aaaaa4&0&0001#{4d1e55b2-f16f-11cf-88cb-001111000030}, \\\\?\\hid#vid_046d&pid_c52b&mi_01&col03#7&33aaaaa4&0&0002#{4d1e55b2-f16f-11cf-88cb-001111000030}, \\\\?\\hid#vid_046d&pid_c52b&mi_01&col04#7&33aaaaa4&0&0003#{4d1e55b2-f16f-11cf-88cb-001111000030}", "manufacturer" : "Logitech", "product" : "USB Receiver", "release" : 4611, "interface" : 0, "usagePage" : "1, 65280, 65280, 65280, 1, 12, 1, 65468", "usage" : "6, 1, 2, 4, 2, 1, 128, 136", "userId" : "asdf@b.com", "__v" : 0 },{ "_id" : { "$oid" : "5a00e5ba1504d9187932691a" }, "vendorId" : 1133, "productId" : 50475, "path" : "\\\\?\\hid#vid_046d&pid_c52b&mi_00#7&fd36ce2&0&0000#{4d1e55b2-f16f-11cf-88cb-001111000030}, \\\\?\\hid#vid_046d&pid_c52b&mi_02&col01#7&3148838c&0&0000#{4d1e55b2-f16f-11cf-88cb-001111000030}, \\\\?\\hid#vid_046d&pid_c52b&mi_02&col02#7&3148838c&0&0001#{4d1e55b2-f16f-11cf-88cb-001111000030}, \\\\?\\hid#vid_046d&pid_c52b&mi_02&col03#7&3148838c&0&0002#{4d1e55b2-f16f-11cf-88cb-001111000030}, \\\\?\\hid#vid_046d&pid_c52b&mi_01&col01#7&33aaaaa4&0&0000#{4d1e55b2-f16f-11cf-88cb-001111000030}, \\\\?\\hid#vid_046d&pid_c52b&mi_01&col02#7&33aaaaa4&0&0001#{4d1e55b2-f16f-11cf-88cb-001111000030}, \\\\?\\hid#vid_046d&pid_c52b&mi_01&col03#7&33aaaaa4&0&0002#{4d1e55b2-f16f-11cf-88cb-001111000030}, \\\\?\\hid#vid_046d&pid_c52b&mi_01&col04#7&33aaaaa4&0&0003#{4d1e55b2-f16f-11cf-88cb-001111000030}", "manufacturer" : "Logitech", "product" : "USB Receiver", "release" : 4611, "interface" : 0, "usagePage" : "1, 65280, 65280, 65280, 1, 12, 1, 65468", "usage" : "6, 1, 2, 4, 2, 1, 128, 136", "userId" : "hellow@u.com", "__v" : 0 },{ "_id" : { "$oid" : "5a00e5ba1504d9187932691b" }, "vendorId" : 48879, "productId" : 65261, "path" : "\\\\?\\hid#lenovovhid#1&632d18&0&0000#{4d1e55b2-f16f-11cf-88cb-001111000030}", "serialNumber" : "UMDF Virtual hidmini device Serial Number string", "manufacturer" : "UMDF Virtual hidmini device Manufacturer string", "product" : "UMDF Virtual hidmini device Product string", "release" : 257, "interface" : -1, "usagePage" : "1", "usage" : "12", "userId" : "hellow@u.com", "__v" : 0 },{ "_id" : { "$oid" : "5a00eeea1504d9187932691f" }, "vendorId" : 1739, "productId" : 29703, "path" : "\\\\?\\hid#syn1b81&col03#5&d0db040&0&0002#{4d1e55b2-f16f-11cf-88cb-001111000030}, \\\\?\\hid#syn1b81&col04#5&d0db040&0&0003#{4d1e55b2-f16f-11cf-88cb-001111000030}, \\\\?\\hid#syn1b81&col01#5&d0db040&0&0000#{4d1e55b2-f16f-11cf-88cb-001111000030}, \\\\?\\hid#syn1b81&col02#5&d0db040&0&0001#{4d1e55b2-f16f-11cf-88cb-001111000030}", "serialNumber" : "9999", "manufacturer" : "Microsoft", "product" : "HIDI2C Device", "release" : 6, "interface" : -1, "usagePage" : "13, 65280, 1, 13", "usage" : "14, 1, 2, 5", "userId" : "Jason2@Thai.com", "__v" : 0 },{ "_id" : { "$oid" : "5a00eeea1504d91879326920" }, "vendorId" : 1133, "productId" : 49279, "path" : "\\\\?\\hid#vid_046d&pid_c07f&mi_00#7&29daa9b0&0&0000#{4d1e55b2-f16f-11cf-88cb-001111000030}, \\\\?\\hid#vid_046d&pid_c07f&mi_01&col01#7&2005023f&0&0000#{4d1e55b2-f16f-11cf-88cb-001111000030}, \\\\?\\hid#vid_046d&pid_c07f&mi_01&col02#7&2005023f&0&0001#{4d1e55b2-f16f-11cf-88cb-001111000030}, \\\\?\\hid#vid_046d&pid_c07f&mi_01&col03#7&2005023f&0&0002#{4d1e55b2-f16f-11cf-88cb-001111000030}, \\\\?\\hid#vid_046d&pid_c07f&mi_01&col04#7&2005023f&0&0003#{4d1e55b2-f16f-11cf-88cb-001111000030}, \\\\?\\hid#vid_046d&pid_c07f&mi_01&col05#7&2005023f&0&0004#{4d1e55b2-f16f-11cf-88cb-001111000030}", "serialNumber" : "057F365D3834", "manufacturer" : "Logitech", "product" : "Gaming Mouse G302", "release" : 37120, "interface" : 0, "usagePage" : "1, 1, 12, 1, 65280, 65280", "usage" : "2, 6, 1, 128, 1, 2", "userId" : "Jason2@Thai.com", "__v" : 0 },{ "_id" : { "$oid" : "5a00eeea1504d91879326921" }, "vendorId" : 11254, "productId" : 41110, "path" : "\\\\?\\hid#hidclass&col01#1&2d595ca7&0&0000#{4d1e55b2-f16f-11cf-88cb-001111000030}, \\\\?\\hid#hidclass&col02#1&2d595ca7&0&0001#{4d1e55b2-f16f-11cf-88cb-001111000030}", "manufacturer" : "Acer Inc.", "product" : "Launch Manager Wireless Device", "release" : 1, "interface" : -1, "usagePage" : "65280, 1", "usage" : "1, 12", "userId" : "Jason2@Thai.com", "__v" : 0 },{ "_id" : { "$oid" : "5a00eef61504d91879326922" }, "vendorId" : 1133, "productId" : 49279, "path" : "\\\\?\\hid#vid_046d&pid_c07f&mi_00#7&29daa9b0&0&0000#{4d1e55b2-f16f-11cf-88cb-001111000030}, \\\\?\\hid#vid_046d&pid_c07f&mi_01&col01#7&2005023f&0&0000#{4d1e55b2-f16f-11cf-88cb-001111000030}, \\\\?\\hid#vid_046d&pid_c07f&mi_01&col02#7&2005023f&0&0001#{4d1e55b2-f16f-11cf-88cb-001111000030}, \\\\?\\hid#vid_046d&pid_c07f&mi_01&col03#7&2005023f&0&0002#{4d1e55b2-f16f-11cf-88cb-001111000030}, \\\\?\\hid#vid_046d&pid_c07f&mi_01&col04#7&2005023f&0&0003#{4d1e55b2-f16f-11cf-88cb-001111000030}, \\\\?\\hid#vid_046d&pid_c07f&mi_01&col05#7&2005023f&0&0004#{4d1e55b2-f16f-11cf-88cb-001111000030}", "serialNumber" : "057F365D3834", "manufacturer" : "This field was changed", "product" : "Gaming Mouse G302", "release" : 37120, "interface" : 0, "usagePage" : "1, 1, 12, 1, 65280, 65280", "usage" : "2, 6, 1, 128, 1, 2", "userId" : "Jason@Thai.com", "__v" : 0 },{ "_id" : { "$oid" : "5a010b6b9740a52f1994f8ce" }, "vendorId" : 48879, "productId" : 65261, "path" : "\\\\?\\hid#lenovovhid#1&632d18&0&0000#{4d1e55b2-f16f-11cf-88cb-001111000030}", "serialNumber" : "UMDF Virtual hidmini device Serial Number string", "manufacturer" : "UMDF Virtual hidmini device Manufacturer string", "product" : "UMDF Virtual hidmini device Product string", "release" : 257, "interface" : -1, "usagePage" : "1", "usage" : "12", "userId" : "hello@emassil.com", "__v" : 0 },{ "_id" : { "$oid" : "5a010b6b9740a52f1994f8cf" }, "vendorId" : 1133, "productId" : 50475, "path" : "\\\\?\\hid#vid_046d&pid_c52b&mi_00#7&fd36ce2&0&0000#{4d1e55b2-f16f-11cf-88cb-001111000030}, \\\\?\\hid#vid_046d&pid_c52b&mi_02&col01#7&3148838c&0&0000#{4d1e55b2-f16f-11cf-88cb-001111000030}, \\\\?\\hid#vid_046d&pid_c52b&mi_02&col02#7&3148838c&0&0001#{4d1e55b2-f16f-11cf-88cb-001111000030}, \\\\?\\hid#vid_046d&pid_c52b&mi_02&col03#7&3148838c&0&0002#{4d1e55b2-f16f-11cf-88cb-001111000030}, \\\\?\\hid#vid_046d&pid_c52b&mi_01&col01#7&33aaaaa4&0&0000#{4d1e55b2-f16f-11cf-88cb-001111000030}, \\\\?\\hid#vid_046d&pid_c52b&mi_01&col02#7&33aaaaa4&0&0001#{4d1e55b2-f16f-11cf-88cb-001111000030}, \\\\?\\hid#vid_046d&pid_c52b&mi_01&col03#7&33aaaaa4&0&0002#{4d1e55b2-f16f-11cf-88cb-001111000030}, \\\\?\\hid#vid_046d&pid_c52b&mi_01&col04#7&33aaaaa4&0&0003#{4d1e55b2-f16f-11cf-88cb-001111000030}", "manufacturer" : "Logitech", "product" : "USB Receiver", "release" : 4611, "interface" : 0, "usagePage" : "1, 65280, 65280, 65280, 1, 12, 1, 65468", "usage" : "6, 1, 2, 4, 2, 1, 128, 136", "userId" : "hello@emassil.com", "__v" : 0 }]
